hexdoc/__init__.py
hexdoc/__main__.py
hexdoc/__version__.py
hexdoc/_hooks.py
hexdoc/py.typed
hexdoc/_export/.gitignore
hexdoc/_export/__init__.py
hexdoc/_export/generated/__init__.py
hexdoc/_export/generated/hexdoc.hexdoc.json
hexdoc/_export/generated/assets/hexdoc/textures/gui/any_block.png
hexdoc/_export/generated/assets/hexdoc/textures/gui/spotlight.png
hexdoc/_export/generated/assets/hexdoc/textures/item/missing.png
hexdoc/_export/generated/assets/minecraft/textures/gui/hexdoc/blast_furnace.png
hexdoc/_export/generated/assets/minecraft/textures/gui/hexdoc/campfire.png
hexdoc/_export/generated/assets/minecraft/textures/gui/hexdoc/crafting_table.png
hexdoc/_export/generated/assets/minecraft/textures/gui/hexdoc/furnace.png
hexdoc/_export/generated/assets/minecraft/textures/gui/hexdoc/smithing_table.png
hexdoc/_export/generated/assets/minecraft/textures/gui/hexdoc/smoker.png
hexdoc/_export/generated/assets/minecraft/textures/gui/hexdoc/stonecutter.png
hexdoc/_export/generated/assets/minecraft/textures/gui/hexdoc/legacy/smithing_table.png
hexdoc/_export/resources/__init__.py
hexdoc/_export/resources/assets/emi/LICENSE
hexdoc/_export/resources/assets/emi/lang/en_us.json
hexdoc/_export/resources/assets/emi/lang/ru_ru.json
hexdoc/_export/resources/assets/emi/lang/zh_cn.json
hexdoc/_export/resources/assets/forge/lang/en_us.json
hexdoc/_export/resources/assets/hexdoc/lang/en_us.flatten.json5
hexdoc/_export/resources/assets/hexdoc/lang/ru_ru.flatten.json5
hexdoc/_export/resources/assets/hexdoc/lang/zh_cn.flatten.json5
hexdoc/_export/resources/assets/hexdoc/textures/gui/any_block.png
hexdoc/_export/resources/assets/hexdoc/textures/gui/spotlight.png
hexdoc/_export/resources/assets/hexdoc/textures/item/missing.png
hexdoc/_export/resources/assets/minecraft/textures/gui/hexdoc/blast_furnace.png
hexdoc/_export/resources/assets/minecraft/textures/gui/hexdoc/campfire.png
hexdoc/_export/resources/assets/minecraft/textures/gui/hexdoc/crafting_table.png
hexdoc-1!0.1.0a35.dist-info/METADATA
hexdoc-1!0.1.0a35.dist-info/WHEEL
hexdoc-1!0.1.0a35.dist-info/entry_points.txt
hexdoc-1!0.1.0a35.dist-info/licenses/LICENSE
hexdoc-1!0.1.0a35.dist-info/RECORD
