Metadata-Version: 2.4
Name: hexdoc
Version: 1!0.1.0a35
Summary: Python web book docgen for Patchouli and Hex Casting.
Project-URL: Homepage, https://hexdoc.hexxy.media
Project-URL: Documentation, https://hexdoc.hexxy.media/docs
Project-URL: Changelog, https://github.com/hexdoc-dev/hexdoc/blob/main/CHANGELOG.md
Project-URL: Source, https://github.com/hexdoc-dev/hexdoc
Project-URL: Demo, https://book.hexxy.media
Author: object-Object, Alwinfy
License: MIT License
License-File: LICENSE
Keywords: hexdoc
Classifier: Intended Audience :: Developers
Classifier: License :: OSI Approved :: MIT License
Classifier: Operating System :: OS Independent
Classifier: Programming Language :: Java
Classifier: Programming Language :: JavaScript
Classifier: Programming Language :: Kotlin
Classifier: Programming Language :: Python :: 3.11
Classifier: Topic :: Documentation
Classifier: Topic :: File Formats :: JSON
Classifier: Topic :: Games/Entertainment
Classifier: Topic :: Internet :: WWW/HTTP :: Dynamic Content
Classifier: Topic :: Software Development :: Libraries :: Python Modules
Classifier: Topic :: Software Development :: Localization
Classifier: Topic :: Text Processing :: Markup :: HTML
Classifier: Typing :: Typed
Requires-Python: >=3.11
Requires-Dist: click<8.2.0
Requires-Dist: frozendict~=2.4
Requires-Dist: hatch~=1.9
Requires-Dist: importlib-resources~=6.0
Requires-Dist: jinja2~=3.1
Requires-Dist: minecraft-render~=2.0.0a6
Requires-Dist: moderngl-window~=2.4
Requires-Dist: moderngl[headless]~=5.10
Requires-Dist: more-itertools~=10.1
Requires-Dist: nbtlib==1.12.1
Requires-Dist: networkx~=3.2
Requires-Dist: ordered-set~=4.1
Requires-Dist: packaging~=23.2
Requires-Dist: pillow~=11.0
Requires-Dist: pluggy~=1.3
Requires-Dist: pydantic!=2.9.0,<3,>=2.7.1
Requires-Dist: pydantic-settings!=2.6.0,~=2.0
Requires-Dist: pygithub~=2.1
Requires-Dist: pyjson5~=1.6
Requires-Dist: requests~=2.31
Requires-Dist: rich~=13.3.4
Requires-Dist: svglib~=1.5.1
Requires-Dist: typer~=0.12
Requires-Dist: typing-extensions~=4.6
Requires-Dist: yarl~=1.9
Provides-Extra: dev
Requires-Dist: copier-template-tester; extra == 'dev'
Requires-Dist: nox[uv]; extra == 'dev'
Requires-Dist: pdoc~=14.1; extra == 'dev'
Requires-Dist: pre-commit; extra == 'dev'
Requires-Dist: pyright==1.1.361; extra == 'dev'
Requires-Dist: pytest-dependency~=0.5; extra == 'dev'
Requires-Dist: pytest-describe~=2.2; extra == 'dev'
Requires-Dist: pytest~=7.4; extra == 'dev'
Requires-Dist: pyyaml-include<2; extra == 'dev'
Requires-Dist: ruff~=0.3.2; extra == 'dev'
Requires-Dist: syrupy~=4.6; extra == 'dev'
Provides-Extra: pdoc
Requires-Dist: pdoc~=14.1; extra == 'pdoc'
Provides-Extra: test
Requires-Dist: copier-template-tester; extra == 'test'
Requires-Dist: pyright==1.1.361; extra == 'test'
Requires-Dist: pytest-dependency~=0.5; extra == 'test'
Requires-Dist: pytest-describe~=2.2; extra == 'test'
Requires-Dist: pytest~=7.4; extra == 'test'
Requires-Dist: pyyaml-include<2; extra == 'test'
Requires-Dist: syrupy~=4.6; extra == 'test'
